jupyterauth_neptune/__init__.py
jupyterauth_neptune/authenticators.py
jupyterauth_neptune/clients.py
jupyterauth_neptune/handlers.py
jupyterauth_neptune-0.2.dist-info/LICENSE
jupyterauth_neptune-0.2.dist-info/WHEEL
jupyterauth_neptune-0.2.dist-info/METADATA
jupyterauth_neptune-0.2.dist-info/RECORD
