Metadata-Version: 2.1
Name: jupyterauth-neptune
Version: 0.2
Summary: Custom JupyterHub authenticator for the Neptune platform.
Home-page: https://github.com/noosenergy/jupyterauth-neptune
License: MIT
Author: Noos Energy
Author-email: contact@noos.energy
Requires-Python: >=3.8,<4.0
Classifier: Development Status :: 5 - Production/Stable
Classifier: Intended Audience :: Developers
Classifier: License :: OSI Approved :: MIT License
Classifier: Operating System :: OS Independent
Classifier: Programming Language :: Python :: 3
Classifier: Programming Language :: Python :: 3.10
Classifier: Programming Language :: Python :: 3.8
Classifier: Programming Language :: Python :: 3.9
Classifier: Typing :: Typed
Requires-Dist: jupyterhub (>=0.8)
Requires-Dist: noos-pyk
Requires-Dist: tornado
Requires-Dist: traitlets
